{"name":"As a User I can reposted the Posts with add my opinion","id":"reactionpost;as-a-user-i-can-reposted-the-posts-with-add-my-opinion","testSteps":[{"number":1,"description":"Given I am on the LinkedIn homepage","duration":9,"startTime":"2023-09-27T00:15:53.223641700+07:00[Asia/Jakarta]","result":"SUCCESS","precondition":false,"level":0,"children":[{"number":2,"description":"User on the LinkedIn home page","duration":0,"startTime":"2023-09-27T00:15:53.231165200+07:00[Asia/Jakarta]","result":"SUCCESS","precondition":false,"level":1}]},{"number":3,"description":"When I see the post that i want to repost it","duration":3,"startTime":"2023-09-27T00:15:53.232650300+07:00[Asia/Jakarta]","result":"SUCCESS","precondition":false,"level":0,"children":[{"number":4,"description":"I see the post that i want to repost it","duration":0,"startTime":"2023-09-27T00:15:53.234657100+07:00[Asia/Jakarta]","result":"SUCCESS","precondition":false,"level":1}]},{"number":5,"description":"And I click icon repost in that posts","duration":3,"startTime":"2023-09-27T00:15:53.236209800+07:00[Asia/Jakarta]","result":"SUCCESS","precondition":false,"level":0,"children":[{"number":6,"description":"I click icon repost in that posts","duration":1,"startTime":"2023-09-27T00:15:53.237216+07:00[Asia/Jakarta]","result":"SUCCESS","precondition":false,"level":1}]},{"number":7,"description":"And I select repost with my thought","duration":1,"startTime":"2023-09-27T00:15:53.239220800+07:00[Asia/Jakarta]","result":"SUCCESS","precondition":false,"level":0,"children":[{"number":8,"description":"I select repost with my thought","duration":0,"startTime":"2023-09-27T00:15:53.240220500+07:00[Asia/Jakarta]","result":"SUCCESS","precondition":false,"level":1}]},{"number":9,"description":"And I write I Agree about this one","duration":1,"startTime":"2023-09-27T00:15:53.242225500+07:00[Asia/Jakarta]","result":"SUCCESS","precondition":false,"level":0,"children":[{"number":10,"description":"I write I Agree about this one","duration":0,"startTime":"2023-09-27T00:15:53.243223300+07:00[Asia/Jakarta]","result":"SUCCESS","precondition":false,"level":1}]},{"number":11,"description":"And I click button post","duration":1,"startTime":"2023-09-27T00:15:53.245220700+07:00[Asia/Jakarta]","result":"SUCCESS","precondition":false,"level":0,"children":[{"number":12,"description":"I click button post","duration":0,"startTime":"2023-09-27T00:15:53.246223400+07:00[Asia/Jakarta]","result":"SUCCESS","precondition":false,"level":1}]},{"number":13,"description":"Then the repost post has been reposted","duration":2,"startTime":"2023-09-27T00:15:53.247724300+07:00[Asia/Jakarta]","result":"SUCCESS","precondition":false,"level":0,"children":[{"number":14,"description":"the repost post has been reposted","duration":1,"startTime":"2023-09-27T00:15:53.247724300+07:00[Asia/Jakarta]","result":"SUCCESS","precondition":false,"level":1}]}],"userStory":{"id":"reactionpost","storyName":"ReactionPost","displayName":"ReactionPost","path":"ReactionPost.feature","narrative":"  As a Linkedin user\n  I want to like, comment and reposted posts\n  So that I can Interactions with another people","type":"feature","qualifiedTag":{"name":"ReactionPost","type":"feature","displayName":"ReactionPost"}},"featureTag":{"name":"ReactionPost","type":"feature","displayName":"ReactionPost"},"title":"As a User I can reposted the Posts with add my opinion","description":"","backgroundTitle":"","backgroundDescription":"","tags":[{"name":"ReactionPost","type":"feature","displayName":"ReactionPost"}],"allTags":[{"name":"ReactionPost","type":"feature","displayName":"ReactionPost"}],"startTime":"2023-09-27T00:15:53.221642300+07:00[Asia/Jakarta]","duration":28,"projectKey":"","isManualTestingUpToDate":false,"manual":false,"testSource":"Cucumber","result":"SUCCESS"}